cfg/__init__.py
cfg/config.py
tfl_api/__init__.py
tfl_api/constants.py
tfl_api/helper_functions.py
tfl_api/tfl_api.py
tfl_api-0.01.dist-info/DESCRIPTION.rst
tfl_api-0.01.dist-info/METADATA
tfl_api-0.01.dist-info/RECORD
tfl_api-0.01.dist-info/WHEEL
tfl_api-0.01.dist-info/metadata.json
tfl_api-0.01.dist-info/top_level.txt
