Metadata-Version: 2.0
Name: tfl-api
Version: 0.01
Summary: Wrapper for Transport for London API
Home-page: http://github.com/juan-m12i/tfl-api-wrapper/
Author: Juan Montalvo Bressi
Author-email: juanm12i@icloud.com
License: MIT
Platform: UNKNOWN
Classifier: Development Status :: 2 - Pre-Alpha
Classifier: Operating System :: POSIX :: Linux
Classifier: Operating System :: MacOS :: MacOS X
Classifier: Operating System :: Unix
Classifier: Environment :: Console
Classifier: Intended Audience :: Developers
Classifier: License :: OSI Approved :: MIT License
Classifier: Programming Language :: Python
Classifier: Programming Language :: Python :: 2.7
